ptic/__init__.py
ptic/neuro_ptic.py
ptic/pmi_tfidf_classifier.py
ptic-0.0.4.dist-info/LICENSE
ptic-0.0.4.dist-info/METADATA
ptic-0.0.4.dist-info/WHEEL
ptic-0.0.4.dist-info/top_level.txt
ptic-0.0.4.dist-info/RECORD
